[
  {
    "commit": "a2435d388",
    "commit_date": "2022-02-16 20:43:49 -0700",
    "loc": 206228,
    "nb_python_files": 419,
    "nb_param_types": 8220,
    "nb_return_types": 3971,
    "nb_variable_types": 2082,
    "nb_warnings": 2569,
    "kind_to_nb": {
      "Undefined attribute [16]": 1117,
      "Incompatible return type [7]": 82,
      "Undefined import [21]": 146,
      "Uninitialized attribute [13]": 387,
      "Incompatible parameter type [6]": 343,
      "Inconsistent override [14]": 55,
      "Invalid type [31]": 57,
      "Undefined or invalid type [11]": 199,
      "Invalid type variable [34]": 12,
      "Invalid inheritance [39]": 5,
      "Incompatible variable type [9]": 75,
      "Inconsistent override [15]": 16,
      "Invalid argument [32]": 1,
      "Unable to unpack [23]": 6,
      "Unsupported operand [58]": 15,
      "Invalid decoration [56]": 5,
      "Missing argument [20]": 1,
      "Illegal annotation target [35]": 4,
      "Call error [29]": 3,
      "Unbound name [10]": 2,
      "Incompatible attribute type [8]": 4,
      "Incompatible overload [43]": 5,
      "Redundant cast [22]": 2,
      "Invalid type parameters [24]": 2,
      "Invalid class instantiation [45]": 6,
      "Invalid method signature [47]": 3,
      "Unexpected keyword [28]": 15,
      "Parsing failure [404]": 1
    }
  },
  {
    "commit": "516c3e39f",
    "commit_date": "2021-07-19 14:13:25 -0700",
    "loc": 185582,
    "nb_python_files": 392,
    "nb_param_types": 7731,
    "nb_return_types": 3698,
    "nb_variable_types": 2058,
    "nb_warnings": 2454,
    "kind_to_nb": {
      "Undefined attribute [16]": 920,
      "Uninitialized attribute [13]": 552,
      "Incompatible return type [7]": 64,
      "Incompatible parameter type [6]": 326,
      "Inconsistent override [14]": 54,
      "Undefined import [21]": 135,
      "Invalid type [31]": 57,
      "Undefined or invalid type [11]": 184,
      "Invalid type variable [34]": 12,
      "Invalid inheritance [39]": 5,
      "Incompatible variable type [9]": 75,
      "Invalid argument [32]": 1,
      "Unable to unpack [23]": 3,
      "Unsupported operand [58]": 7,
      "Invalid decoration [56]": 5,
      "Missing argument [20]": 1,
      "Illegal annotation target [35]": 4,
      "Call error [29]": 3,
      "Unbound name [10]": 2,
      "Incompatible attribute type [8]": 4,
      "Incompatible overload [43]": 5,
      "Inconsistent override [15]": 14,
      "Redundant cast [22]": 2,
      "Invalid type parameters [24]": 2,
      "Invalid class instantiation [45]": 6,
      "Invalid method signature [47]": 3,
      "Unexpected keyword [28]": 7,
      "Parsing failure [404]": 1
    }
  },
  {
    "commit": "9b122318a",
    "commit_date": "2020-10-01 17:11:04 -0700",
    "loc": 153381,
    "nb_python_files": 383,
    "nb_param_types": 6107,
    "nb_return_types": 2900,
    "nb_variable_types": 1576,
    "nb_warnings": 2112,
    "kind_to_nb": {
      "Undefined import [21]": 136,
      "Invalid decoration [56]": 8,
      "Unexpected keyword [28]": 9,
      "Undefined or invalid type [11]": 142,
      "Uninitialized attribute [13]": 520,
      "Undefined attribute [16]": 726,
      "Incompatible parameter type [6]": 280,
      "Inconsistent override [14]": 43,
      "Invalid type [31]": 39,
      "Invalid type variable [34]": 6,
      "Invalid inheritance [39]": 5,
      "Incompatible variable type [9]": 92,
      "Invalid argument [32]": 1,
      "Incompatible attribute type [8]": 8,
      "Inconsistent override [15]": 13,
      "Incompatible return type [7]": 46,
      "Unable to unpack [23]": 2,
      "Unsupported operand [58]": 10,
      "Missing argument [20]": 1,
      "Illegal annotation target [35]": 4,
      "Unbound name [10]": 2,
      "Call error [29]": 2,
      "Redundant cast [22]": 3,
      "Invalid type parameters [24]": 4,
      "Invalid class instantiation [45]": 5,
      "Invalid method signature [47]": 3,
      "Incompatible overload [43]": 1,
      "Parsing failure [404]": 1
    }
  },
  {
    "commit": "6c9c3f552",
    "commit_date": "2019-11-27 21:32:04 -0500",
    "loc": 121146,
    "nb_python_files": 369,
    "nb_param_types": 3513,
    "nb_return_types": 1724,
    "nb_variable_types": 1057,
    "nb_warnings": 1595,
    "kind_to_nb": {
      "Undefined import [21]": 138,
      "Invalid decoration [56]": 7,
      "Unexpected keyword [28]": 4,
      "Incompatible parameter type [6]": 145,
      "Undefined attribute [16]": 413,
      "Uninitialized attribute [13]": 486,
      "Inconsistent override [14]": 38,
      "Invalid type [31]": 39,
      "Undefined or invalid type [11]": 153,
      "Call error [29]": 5,
      "Invalid type variable [34]": 5,
      "Invalid inheritance [39]": 5,
      "Incompatible variable type [9]": 92,
      "Unsupported operand [58]": 3,
      "Missing argument [20]": 2,
      "Illegal annotation target [35]": 4,
      "Incompatible return type [7]": 37,
      "Unbound name [10]": 1,
      "Incompatible attribute type [8]": 3,
      "Inconsistent override [15]": 3,
      "Invalid type parameters [24]": 4,
      "Invalid class instantiation [45]": 5,
      "Unable to unpack [23]": 2,
      "Parsing failure [404]": 1
    }
  },
  {
    "commit": "d91a16d51",
    "commit_date": "2019-01-18 18:37:09 -0500",
    "loc": 88630,
    "nb_python_files": 336,
    "nb_param_types": 1621,
    "nb_return_types": 660,
    "nb_variable_types": 771,
    "nb_warnings": 1700,
    "kind_to_nb": {
      "Undefined import [21]": 89,
      "Invalid type [31]": 44,
      "Undefined or invalid type [11]": 106,
      "Call error [29]": 4,
      "Invalid inheritance [39]": 20,
      "Incompatible variable type [9]": 58,
      "Incompatible parameter type [6]": 221,
      "Inconsistent override [15]": 8,
      "Uninitialized attribute [13]": 528,
      "Unexpected keyword [28]": 3,
      "Inconsistent override [14]": 6,
      "Incompatible return type [7]": 64,
      "Undefined attribute [16]": 520,
      "Too many arguments [19]": 1,
      "Incompatible attribute type [8]": 14,
      "Unable to unpack [23]": 10,
      "Unbound name [10]": 1,
      "Missing argument [20]": 1,
      "Invalid argument [32]": 1,
      "Illegal annotation target [35]": 1
    }
  },
  {
    "commit": "7beafd004",
    "commit_date": "2017-05-12 15:08:25 -0400",
    "loc": 56426,
    "nb_python_files": 307,
    "nb_param_types": 698,
    "nb_return_types": 215,
    "nb_variable_types": 479,
    "nb_warnings": 1184,
    "kind_to_nb": {
      "Invalid type [31]": 63,
      "Undefined or invalid type [11]": 115,
      "Undefined import [21]": 38,
      "Undefined attribute [16]": 333,
      "Call error [29]": 9,
      "Invalid inheritance [39]": 18,
      "Inconsistent override [15]": 6,
      "Incompatible parameter type [6]": 123,
      "Uninitialized attribute [13]": 402,
      "Incompatible variable type [9]": 55,
      "Unsupported operand [58]": 2,
      "Incompatible return type [7]": 10,
      "Incompatible attribute type [8]": 10
    }
  },
  {
    "commit": "412d38767",
    "commit_date": "2015-11-17 16:37:06 -0500",
    "loc": 40172,
    "nb_python_files": 357,
    "nb_param_types": 99,
    "nb_return_types": 1,
    "nb_variable_types": 0,
    "nb_warnings": 1472,
    "kind_to_nb": {
      "Undefined import [21]": 556,
      "Undefined or invalid type [11]": 480,
      "Too many arguments [19]": 53,
      "Undefined attribute [16]": 43,
      "Invalid type [31]": 84,
      "Incompatible variable type [9]": 17,
      "Unexpected keyword [28]": 26,
      "Invalid decoration [56]": 16,
      "Invalid Exception [48]": 6,
      "Invalid inheritance [39]": 16,
      "Inconsistent override [15]": 120,
      "Call error [29]": 5,
      "Incompatible parameter type [6]": 45,
      "Parsing failure [404]": 1,
      "Unbound name [10]": 4
    }
  },
  {
    "commit": "58d2116d8",
    "commit_date": "2012-12-05 16:16:56 -0500",
    "loc": 39598,
    "nb_python_files": 341,
    "nb_param_types": 60,
    "nb_return_types": 0,
    "nb_variable_types": 0,
    "nb_warnings": 1357,
    "kind_to_nb": {
      "Undefined import [21]": 493,
      "Undefined or invalid type [11]": 469,
      "Too many arguments [19]": 42,
      "Invalid type [31]": 87,
      "Incompatible variable type [9]": 15,
      "Unexpected keyword [28]": 26,
      "Undefined attribute [16]": 34,
      "Invalid decoration [56]": 15,
      "Invalid Exception [48]": 6,
      "Inconsistent override [15]": 116,
      "Call error [29]": 5,
      "Invalid inheritance [39]": 11,
      "Parsing failure [404]": 1,
      "Incompatible parameter type [6]": 34,
      "Unbound name [10]": 3
    }
  },
  {
    "commit": "f9c5e4fc8",
    "commit_date": "2011-03-03 17:56:52 -0500",
    "loc": 22099,
    "nb_python_files": 200,
    "nb_param_types": 28,
    "nb_return_types": 2,
    "nb_variable_types": 0,
    "nb_warnings": 804,
    "kind_to_nb": {
      "Undefined import [21]": 290,
      "Undefined or invalid type [11]": 325,
      "Too many arguments [19]": 31,
      "Invalid type [31]": 73,
      "Incompatible variable type [9]": 3,
      "Unexpected keyword [28]": 26,
      "Undefined attribute [16]": 33,
      "Invalid decoration [56]": 3,
      "Invalid Exception [48]": 3,
      "Parsing failure [404]": 1,
      "Inconsistent override [15]": 2,
      "Incompatible parameter type [6]": 8,
      "Unbound name [10]": 3,
      "Invalid inheritance [39]": 3
    }
  },
  {
    "commit": "0288121f3",
    "commit_date": "2008-09-30 20:16:16 -0400",
    "loc": 0,
    "nb_python_files": 0,
    "nb_param_types": 0,
    "nb_return_types": 0,
    "nb_variable_types": 0,
    "nb_warnings": 0,
    "kind_to_nb": {}
  }
]