[
    {
        "execution_time": "",
        "machine": {
            "OS": "Linux-4.15.0-166-generic-x86_64-with-Ubuntu-18.04-bionic",
            "CPU": "x86_64",
            "CORES": 48
        },
        "total_repositories": 1,
        "total_commits": 1714,
        "commit_year_dict": {
            "2016": 262,
            "2017": 205,
            "2018": 145,
            "2019": 520,
            "2020": 197,
            "2021": 385
        },
        "loc_year_edit": {
            "2016": 265119,
            "2017": 21160,
            "2018": 15137,
            "2019": 51358,
            "2020": 138430,
            "2021": 52927
        },
        "s0": "------------------------------------------------------------------------",
        "RQ0": "How many types are used?",
        "code_changes": [],
        "commit_statistics": [],
        "repo_with_types_changes": 1,
        "percentage_repo_with_typeChanges": "",
        "commits_with_typeChanges": 152,
        "percentage_commits_with_typeChanges": "",
        "total_typeAnnotation_codeChanges": 5368,
        "s1": "------------------------------------------------------------------------",
        "RQ1": "Are type annotation inserted, removed and changed?",
        "insert_types": {
            "2020": 1881,
            "2021": 1312
        },
        "percentage_insert_types": "",
        "remove_types": {
            "2020": 932,
            "2021": 1001
        },
        "percentage_remove_types": "",
        "modify_existing_types": {
            "2020": 30,
            "2021": 212
        },
        "percentage_modify_existing_types": "",
        "s2": "------------------------------------------------------------------------",
        "RQ2_1": "What types are added (generic, numeric, ...)?",
        "anyType_added": 0,
        "noneType_added": 0,
        "numericType_added": 0,
        "binarySequenceType_added": 0,
        "textSequenceType_added": 0,
        "mappingTypes_added": 0,
        "setTypes_added": 0,
        "sequenceType_added": 0,
        "newType_added": 0,
        "total_added": 3193,
        "RQ2_2": "What are the top 5 types added?",
        "typeAdded_dict": {
            "str": 387,
            "spacylang": 2,
            "list [spacydoc]": 1,
            "list [int]": 5,
            "int": 315,
            "union [str,spacylang]": 3,
            "optional [corpusdata]": 2,
            "none": 58,
            "corpusdata": 2,
            "iterable [str]": 68,
            "tuple [str,dict]": 3,
            "iterable [tuple [str,dict]]": 16,
            "spacydoc": 2,
            "iterable [spacydoc]": 1,
            "callable [...,bool]": 9,
            "optional [int]": 74,
            "iterator [spacydoc]": 1,
            "iterable [int]": 2,
            "bool": 217,
            "np.ndarray": 21,
            "dict [union [int,str],union [int,float]]": 8,
            "union [str,pathlib]": 60,
            "\"corpus\"": 2,
            "union [counter [any],dict [any,union [int,float]]]": 4,
            "union [doc,span]": 12,
            "optional [union [str,set [str]]]": 66,
            "iterable [token]": 26,
            "iterable [span]": 27,
            "doc": 156,
            "union [str,list [str],list [dict],list [list [dict]]]": 5,
            "callable": 3,
            "list [dict]": 2,
            "iterable [tuple [span,span,span]]": 2,
            "optional [dict [str,str]]": 10,
            "dict [str,list [tuple [str,float]]]": 5,
            "dict [str,list [str]]": 5,
            "span": 7,
            "float": 133,
            "tuple [str,float]": 5,
            "iterable [tuple [span,token,span]]": 2,
            "dict [str,int]": 27,
            "optional [dict [str,float]]": 14,
            "optional [str]": 99,
            "optional [set [str]]": 11,
            "optional [iterable [tuple [str,str,str]]]": 2,
            "union [doc,span,token]": 4,
            "union [str,sequence [str]]": 4,
            "union [sequence [str],sequence [token]]": 2,
            "union [str,bool,callable [...,str]]": 4,
            "nx.graph": 35,
            "union [sequence [str],sequence [span]]": 2,
            "dict [str,any]": 6,
            "union [dict [any,any],iterable [tuple [any,any]]]": 2,
            "any": 14,
            "union [type [any],tuple [type [any],...]]": 4,
            "type [any]": 2,
            "optional [collection [any]]": 2,
            "union [str,bytes]": 10,
            "bytes": 2,
            "pathlib.path": 6,
            "union [any,set [any]]": 2,
            "optional [set [any]]": 2,
            "set [any]": 2,
            "sequence [any]": 2,
            "optional [union [type [any],tuple [type [any],...]]]": 2,
            "tuple [any,any]": 4,
            "set [str]": 93,
            "dict [str,dict [str,str]]": 2,
            "pattern": 49,
            "dict [int,int]": 9,
            "sequence [callable]": 2,
            "optional [union [int,float,sequence [float]]]": 2,
            "list [aug_utils]": 38,
            "union [int,float]": 34,
            "iterable [list [str]]": 2,
            "list [augtok]": 4,
            "list [tuple [str,int]]": 2,
            "dict": 12,
            "tuple [str,str]": 10,
            "set [int]": 2,
            "optional [union [int,set [int]]]": 14,
            "optional [tuple [optional [str],optional [str]]]": 20,
            "tuple [int,int]": 13,
            "optional [tuple [optional [int],optional [int]]]": 10,
            "tuple [str,...]": 3,
            "tuple [optional [str],optional [str]]": 2,
            "dict [int,optional [str]]": 4,
            "dict [str,str]": 9,
            "optional [list [dict [str,any]]]": 3,
            "union [sequence [str],sequence [token],sequence [span]]": 3,
            "optional [union [str,callable [...,str]]]": 30,
            "dict [any,float]": 10,
            "defaultdict": 6,
            "optional [np]": 5,
            "dict [str,float]": 36,
            "optional [union [str,collection [str]]]": 23,
            "list [tuple [str,float]]": 21,
            "counter [tuple [str,str]]": 4,
            "dict [tuple [str,str],int]": 4,
            "defaultdict [str,float]": 3,
            "set [tuple [str,...]]": 8,
            "defaultdict [tuple,int]": 3,
            "union [int,collection [int]]": 9,
            "tuple [int,...]": 14,
            "tuple [list [tuple [str,int,int,int]],counter [str]]": 1,
            "list [tuple [str,int,int,int]]": 3,
            "counter [str]": 4,
            "tuple [list [tuple [str,int,int,int]],set [str]]": 1,
            "defaultdict [str,defaultdict [str,int]]": 5,
            "defaultdict [str,defaultdict [str,float]]": 6,
            "list [tuple [str,str,dict [str,float]]]": 8,
            "optional [union [str,callable]]": 3,
            "union [iterable [span],iterable [token]]": 3,
            "list [set [str]]": 5,
            "iterable [tuple [token,...]]": 15,
            "iterable [tuple [str,float]]": 5,
            "optional [float]": 16,
            "iterable [iterable [str]]": 17,
            "iterable [bool]": 5,
            "tuple [list [str],list [str]]": 5,
            "dict [int,dict [str,list]]": 8,
            "defaultdict [int,dict]": 3,
            "dict [int,float]": 13,
            "list [token]": 17,
            "list [tuple [token,...]]": 4,
            "optional [union [str,sequence [str]]]": 2,
            "union [str,type [csv]]": 2,
            "iterable [union [list,dict]]": 2,
            "union [csv,iterator]": 2,
            "union [iterable [dict [str,any]],iterable [iterable]]": 2,
            "optional [sequence [str]]": 2,
            "union [csv,any]": 2,
            "optional [tuple [str,str]]": 4,
            "union [iterable [str],iterable [bytes]]": 2,
            "iterable": 10,
            "optional [union [int,str]]": 2,
            "union [sp,sp]": 4,
            "optional [union [str,language]]": 2,
            "iterable [doc]": 6,
            "union [doc,iterable [doc]]": 2,
            "sequence [str]": 11,
            "optional [bool]": 6,
            "union [str,iterable [str]]": 2,
            "io": 2,
            "union [str,int]": 2,
            "tuple": 2,
            "optional [tuple [str,...]]": 2,
            "language": 8,
            "union [str,tuple [str,dict],doc]": 2,
            "union [str,callable [...,str],language]": 8,
            "list [list [str]]": 3,
            "list [list [tuple [str,str]]]": 2,
            "optional [union [int,collection [int]]]": 4,
            "union [iterable [int],iterable [str]]": 2,
            "list [iterable [span]]": 2,
            "union [set [str],dict [str,any]]": 4,
            "union [str,language]": 5,
            "list [str]": 26,
            "list [bool]": 2,
            "token": 20,
            "union [span,token]": 2,
            "list [doc]": 1,
            "tuple [str,dict [any,any]]": 1,
            "iterator [doc]": 1,
            "list [candidate]": 9,
            "tuple [list [candidate],counter [str]]": 3,
            "tuple [list [candidate],set [str]]": 3,
            "tuple [union [span,token],union [span,token],span]": 1,
            "collection [any]": 1,
            "type": 2,
            "union [int,slice]": 1,
            "collection [str]": 5,
            "union [doc,iterable [token]]": 6,
            "collection [int]": 2,
            "dict [int,str]": 6,
            "optional [union [str,iterable [str]]]": 1,
            "callable [...,str]": 3,
            "optional [...]": 57,
            "iterable [tuple [list [token],list [token],list [token]]]": 5,
            "iterable [tuple [str,str,str]]": 2,
            "tuple [...,...,span]": 1,
            "iterable [tuple [list [token],list [token],span]]": 2,
            "optional [callable]": 2,
            "list [dict [str,str]]": 2,
            "list [tuple [str,str]]": 12,
            "sequence [int]": 3,
            "model": 10,
            "model [list [str],thinc]": 9,
            "model [list [str],list [list [str]]]": 3,
            "tuple [list [list [str]],callable]": 3,
            "list [list [tuple [str,float]]]": 3,
            "argparse.namespace": 1,
            "docdata": 1,
            "langlike": 5,
            "types.langlike": 6,
            "sequence [augtransform]": 1,
            "tuple [augtransform]": 1,
            "list [augtransform]": 1,
            "types.doclike": 24,
            "types.langlikeincontext": 2,
            "optional [iterable [str]]": 1,
            "types.pathlike": 8,
            "callable [...,float]": 3,
            "iterable [...]": 2,
            "optional [callable [...,str]]": 1,
            "\"charngramstokenizer\"": 1,
            "iterable [tuple [str,...]]": 2,
            "iterable [types]": 3,
            "tuple [docliketospans,...]": 1,
            "optional [callable [...,iterable [span]]]": 1,
            "optional [docliketospans]": 5,
            "\"termstokenizer\"": 1,
            "dict [str,dict [str,any]]": 8,
            "list [docliketospans]": 1,
            "dict [any,int]": 2,
            "sequence [sequence [str]]": 1,
            "\"vectorizer\"": 1,
            "sp.csr_matrix": 21,
            "tuple [sp,dict [str,int]]": 5,
            "\"groupvectorizer\"": 1,
            "tuple [sp,dict [str,int],dict [str,int]]": 1,
            "callable [...,any]": 1,
            "optional [any]": 1,
            "union [dict,defaultdict]": 1,
            "optional [tuple [int,...]]": 2,
            "tuple [list [token],list [token],list [token]]": 2,
            "tuple [list [token],list [token],span]": 1,
            "list [callable [...,bool]]": 1,
            "optional [dict [str,dict [str,any]]]": 2,
            "list [dict [str,any]]": 1,
            "literal [\"linear\",\"sqrt\",\"log\"]": 2,
            "literal [\"standard\",\"smooth\",\"bm25\"]": 2,
            "tuple [dict [str,int],bool]": 1,
            "optional [dict]": 2,
            "classvar [dict [str,int]]": 1,
            "classvar [dict [str,str]]": 2,
            "dict [str,dict [str,dict [str,list [str]]]]": 5,
            "tuple [str,str,str]": 1,
            "classvar [dict [any,str]]": 1,
            "classvar [tuple [str,str,str]]": 1,
            "literal [\"en\",\"it\"]": 1,
            "literal [\"token\",\"lemma\",\"lemmapos\"]": 1,
            "dict [str,dict [str,float]]": 1,
            "classvar [set [str]]": 1,
            "\"topicmodel\"": 1,
            "literal [\"index\",\"weight\"]": 1,
            "literal [\"topic_weight\",\"corpus_weight\"]": 1,
            "literal [\"seriation\",\"weight\",\"index\",\"alphabetical\"]": 1,
            "types.anystr": 3,
            "dict [str,dict [str,int]]": 2,
            "literal [\"standard\",\"root\",\"corrected\"]": 1,
            "literal [\"herdan\",\"summer\",\"dugast\"]": 1,
            "literal [\"mean\",\"moving_avg\"]": 1,
            "dict [str,callable [...,float]]": 1,
            "dict [str,tuple [callable [...,float],optional [str]]]": 1,
            "tuple [token,...]": 3,
            "readabilitynametype": 2,
            "diversitynametype": 1,
            "types.docortokens": 17,
            "tokengroupbytype": 1,
            "weightingtype": 3,
            "spangroupbytype": 1,
            "dict [str,dict [str,types]]": 22
        },
        "RQ2_3": "What types are removed (generic, numeric, ...)?",
        "anyType_removed": 0,
        "noneType_removed": 0,
        "numericType_removed": 0,
        "binarySequenceType_removed": 0,
        "textSequenceType_removed": 0,
        "mappingTypes_removed": 0,
        "setTypes_removed": 0,
        "sequenceType_removed": 0,
        "newType_removed": 0,
        "total_removed": 1933,
        "RQ2_4": "What are the top 5 types removed?",
        "typeRemoved_dict": {
            "sequence [callable]": 1,
            "optional [union [int,float,sequence [float]]]": 1,
            "doc": 110,
            "list [aug_utils]": 20,
            "union [int,float]": 34,
            "optional [union [str,set [str]]]": 40,
            "optional [str]": 43,
            "union [doc,span]": 12,
            "iterable [list [str]]": 1,
            "str": 221,
            "list [augtok]": 1,
            "list [tuple [str,int]]": 1,
            "pathlib.path": 3,
            "set [str]": 65,
            "dict [str,dict [str,str]]": 2,
            "pattern": 24,
            "language": 6,
            "list [doc]": 1,
            "list [int]": 3,
            "int": 231,
            "union [str,language]": 6,
            "optional [corpusdata]": 1,
            "corpusdata": 1,
            "iterable [str]": 37,
            "tuple [str,dict [any,any]]": 1,
            "iterable [tuple [str,dict]]": 8,
            "iterable [doc]": 2,
            "callable [...,bool]": 6,
            "optional [int]": 30,
            "iterable [int]": 1,
            "bool": 135,
            "union [counter [any],dict [any,union [int,float]]]": 2,
            "union [str,pathlib]": 35,
            "none": 33,
            "iterator [doc]": 1,
            "np.ndarray": 5,
            "dict [union [int,str],union [int,float]]": 4,
            "\"corpus\"": 1,
            "dict": 7,
            "tuple [str,str]": 5,
            "set [int]": 1,
            "optional [union [int,set [int]]]": 7,
            "optional [tuple [optional [str],optional [str]]]": 10,
            "tuple [int,int]": 7,
            "optional [tuple [optional [int],optional [int]]]": 5,
            "dict [str,any]": 2,
            "tuple [optional [str],optional [str]]": 1,
            "tuple [str,...]": 1,
            "dict [int,optional [str]]": 2,
            "dict [str,str]": 4,
            "optional [list [dict [str,any]]]": 1,
            "union [str,list [str],list [dict],list [list [dict]]]": 4,
            "callable": 2,
            "optional [dict [str,str]]": 8,
            "dict [str,list [tuple [str,float]]]": 4,
            "span": 5,
            "float": 87,
            "iterable [token]": 17,
            "iterable [span]": 19,
            "list [dict]": 1,
            "iterable [tuple [span,span,span]]": 2,
            "dict [str,list [str]]": 4,
            "tuple [str,float]": 4,
            "iterable [tuple [span,token,span]]": 2,
            "optional [union [str,sequence [str]]]": 1,
            "union [str,type [csv]]": 2,
            "union [csv,iterator]": 1,
            "union [iterable [dict [str,any]],iterable [iterable]]": 2,
            "optional [sequence [str]]": 1,
            "union [csv,any]": 1,
            "iterable [union [list,dict]]": 2,
            "optional [tuple [str,str]]": 2,
            "union [iterable [str],iterable [bytes]]": 2,
            "any": 5,
            "optional [union [int,str]]": 1,
            "iterable": 5,
            "union [sp,sp]": 4,
            "optional [union [str,language]]": 1,
            "union [doc,iterable [doc]]": 2,
            "sequence [str]": 6,
            "optional [bool]": 6,
            "union [str,iterable [str]]": 2,
            "union [str,bytes]": 8,
            "union [str,int]": 2,
            "io": 1,
            "tuple": 1,
            "union [sequence [str],sequence [token],sequence [span]]": 3,
            "optional [union [str,callable [...,str]]]": 19,
            "nx.graph": 28,
            "defaultdict": 6,
            "optional [np]": 4,
            "dict [any,float]": 8,
            "dict [str,float]": 25,
            "optional [union [str,collection [str]]]": 18,
            "counter [tuple [str,str]]": 3,
            "dict [tuple [str,str],int]": 3,
            "dict [str,int]": 17,
            "defaultdict [str,float]": 3,
            "defaultdict [tuple,int]": 3,
            "list [tuple [str,float]]": 16,
            "set [tuple [str,...]]": 6,
            "union [int,collection [int]]": 9,
            "tuple [int,...]": 8,
            "list [candidate]": 9,
            "counter [str]": 3,
            "optional [dict [str,float]]": 11,
            "defaultdict [str,defaultdict [str,int]]": 5,
            "defaultdict [str,defaultdict [str,float]]": 6,
            "list [tuple [str,str,dict [str,float]]]": 6,
            "tuple [list [candidate],counter [str]]": 3,
            "tuple [list [candidate],set [str]]": 3,
            "optional [union [str,callable]]": 2,
            "optional [set [str]]": 7,
            "union [iterable [span],iterable [token]]": 3,
            "iterable [tuple [str,float]]": 4,
            "optional [float]": 11,
            "iterable [iterable [str]]": 5,
            "iterable [bool]": 5,
            "list [set [str]]": 4,
            "iterable [tuple [token,...]]": 12,
            "tuple [list [str],list [str]]": 5,
            "dict [int,dict [str,list]]": 6,
            "dict [int,int]": 7,
            "defaultdict [int,dict]": 3,
            "dict [int,float]": 9,
            "list [tuple [token,...]]": 3,
            "union [sequence [str],sequence [token]]": 2,
            "union [str,bool,callable [...,str]]": 4,
            "union [sequence [str],sequence [span]]": 2,
            "union [doc,span,token]": 4,
            "union [str,sequence [str]]": 4,
            "optional [tuple [str,...]]": 2,
            "union [str,tuple [str,dict],doc]": 2,
            "union [str,callable [...,str],language]": 8,
            "tuple [str,dict]": 1,
            "optional [union [int,collection [int]]]": 2,
            "list [iterable [span]]": 2,
            "union [set [str],dict [str,any]]": 4,
            "list [list [str]]": 3,
            "list [list [tuple [str,str]]]": 2,
            "union [iterable [int],iterable [str]]": 2,
            "list [str]": 10,
            "list [bool]": 2,
            "token": 12,
            "union [span,token]": 2,
            "list [token]": 10,
            "optional [iterable [tuple [str,str,str]]]": 1,
            "union [dict [any,any],iterable [tuple [any,any]]]": 2,
            "union [type [any],tuple [type [any],...]]": 4,
            "type [any]": 1,
            "union [any,set [any]]": 2,
            "optional [set [any]]": 1,
            "tuple [any,any]": 3,
            "optional [union [type [any],tuple [type [any],...]]]": 1,
            "optional [collection [any]]": 1,
            "bytes": 1,
            "set [any]": 1,
            "collection [str]": 5,
            "iterable [tuple [list [token],list [token],list [token]]]": 3,
            "tuple [...,...,span]": 1,
            "union [str,list [str],list [dict [str,str]],list [list [dict [str,str]]]]": 1,
            "list [dict [str,str]]": 2,
            "tuple [union [span,token],union [span,token],span]": 1,
            "optional [...]": 34,
            "iterable [tuple [str,str,str]]": 1,
            "optional [callable]": 1,
            "iterable [tuple [list [token],list [token],span]]": 1,
            "sequence [int]": 2,
            "model": 6,
            "model [list [str],thinc]": 6,
            "model [list [str],list [list [str]]]": 2,
            "tuple [list [list [str]],callable]": 2,
            "list [tuple [str,str]]": 4,
            "list [list [tuple [str,float]]]": 1,
            "types.langlikeincontext": 1,
            "callable [...,float]": 2,
            "union [int,slice]": 1,
            "dict [str,dict [str,any]]": 6,
            "dict [...,...]": 4,
            "sequence [sequence [str]]": 1,
            "type": 2,
            "dict [int,str]": 2,
            "union [doc,iterable [token]]": 6,
            "dict [str,dict [str,int]]": 2,
            "tuple [token,...]": 2,
            "types.docortokens": 1,
            "collection [int]": 1,
            "dict [str,callable [...,float]]": 1,
            "dict [str,tuple [callable [...,float],optional [str]]]": 1,
            "types.langlike": 1,
            "types.doclike": 4,
            "tokengroupbytype": 1,
            "weightingtype": 3,
            "spangroupbytype": 1,
            "dict [any,int]": 1,
            "dict [str,dict [str,types]]": 8
        },
        "RQ2_5": "What types are the top 10 changed ?",
        "total_changed": 242,
        "typeChanged_dict_var": {
            "spacylang -> language": 1,
            "list [spacydoc] -> list [doc]": 1,
            "set [str] -> dict [str,set [str]]": 1,
            "list [aug_utils] -> list [types]": 2,
            "tuple [str,str] -> classvar [tuple [str,str]]": 4,
            "set [str] -> classvar [set [str]]": 4,
            "set [int] -> classvar [set [int]]": 1,
            "tuple [int,int] -> classvar [tuple [int,int]]": 2,
            "dict [int,optional [str]] -> classvar [dict [int,optional [str]]]": 2,
            "dict [str,str] -> classvar [dict [str,str]]": 1
        },
        "typeChanged_dict_arg": {
            "union [str,spacylang] -> union [str,language]": 3,
            "tuple [str,dict] -> tuple [str,dict [any,any]]": 1,
            "spacydoc -> doc": 2,
            "iterable [spacydoc] -> iterable [doc]": 1,
            "list [tuple [str,int,int,int]] -> list [candidate]": 3,
            "list [token] -> iterable [token]": 1,
            "dict [int,float] -> dict [int,int]": 1,
            "sequence [any] -> tuple [any,any]": 2,
            "str -> literal [\"cooc_freq\",\"binary\"]": 1,
            "str -> literal [\"cosine\",\"jaccard\"]": 1,
            "literal [\"cooc_freq\",\"binary\"] -> str": 1,
            "literal [\"cosine\",\"jaccard\"] -> str": 1,
            "union [str,list [str],list [dict],list [list [dict]]] -> union [str,list [str],list [dict [str,str]],list [list [dict [str,str]]]]": 1,
            "sequence [str] -> collection [str]": 1,
            "optional [union [str,set [str]]] -> optional [union [str,collection [str]]]": 1,
            "optional [union [str,collection [str]]] -> optional [...]": 7,
            "optional [union [str,callable [...,str]]] -> optional [...]": 11,
            "optional [union [str,callable]] -> optional [...]": 1,
            "optional [union [str,iterable [str]]] -> optional [union [str,collection [str]]]": 1,
            "optional [union [int,collection [int]]] -> optional [...]": 2,
            "docdata -> types.docdata": 1,
            "langlike -> types.langlikeincontext": 5,
            "tuple [str,dict] -> types.record": 1,
            "sequence [callable] -> sequence [augtransform]": 1,
            "optional [union [int,float,sequence [float]]] -> optional [...]": 1,
            "optional [union [str,set [str]]] -> optional [...]": 25,
            "types.langlikeincontext -> language": 1,
            "optional [union [str,language]] -> optional [types]": 1,
            "union [str,pathlib] -> types.pathlike": 23,
            "optional [union [str,sequence [str]]] -> optional [...]": 1,
            "optional [union [int,str]] -> optional [...]": 1,
            "union [str,pathlib] -> optional [types]": 1,
            "union [str,language] -> types.langlike": 2,
            "optional [corpusdata] -> optional [types]": 1,
            "corpusdata -> types.corpusdata": 1,
            "tuple [str,dict [any,any]] -> types.record": 1,
            "iterable [tuple [str,dict]] -> iterable [types]": 1,
            "iterable [str] -> iterable [types]": 1,
            "iterable [types] -> set [str]": 1,
            "optional [set [any]] -> optional [set [types]]": 1,
            "tuple [any,any] -> tuple [types,types]": 2,
            "optional [union [type [any],tuple [type [any],...]]] -> optional [...]": 1,
            "sequence [augtransform] -> sequence [types]": 2,
            "list [aug_utils] -> list [types]": 8,
            "optional [union [int,set [int]]] -> optional [...]": 7,
            "str -> literal [\"count\",\"binary\"]": 1,
            "str -> literal [\"linear\",\"sqrt\",\"log\",\"binary\"]": 4,
            "optional [str] -> optional [literal [\"standard\",\"smooth\",\"bm25\"]]": 4,
            "optional [str] -> optional [literal [\"linear\",\"sqrt\",\"log\"]]": 4,
            "optional [str] -> optional [literal [\"l1\",\"l2\"]]": 2,
            "str -> formattype": 2,
            "str -> literal [\"infer\",\"bz2\",\"gzip\",\"xz\",\"zip\"]": 1,
            "str -> literal [\"lemma\",\"lower\",\"norm\",\"orth\",\"lemma_\",\"lower_\",\"norm_\",\"orth_\"]": 2,
            "str -> literal [\"count\",\"freq\"]": 1,
            "str -> literal [\"count\",\"freq\",\"idf\"]": 1,
            "str -> tokengroupbytype": 1,
            "str -> weightingtype": 3,
            "str -> spangroupbytype": 1,
            "str -> literal [\"nfc\",\"nfd\",\"nfkc\",\"nfkd\"]": 1,
            "literal [\"mean\",\"moving_avg\"] -> literal [\"mean\",\"moving-avg\"]": 1,
            "str -> optional [str]": 1,
            "readabilitynametype -> countsnametype": 1
        },
        "typeChanged_dict_ret": {
            "iterator [spacydoc] -> iterator [doc]": 1,
            "spacylang -> language": 1,
            "tuple [list [tuple [str,int,int,int]],counter [str]] -> tuple [list [candidate],counter [str]]": 1,
            "tuple [list [tuple [str,int,int,int]],set [str]] -> tuple [list [candidate],set [str]]": 1,
            "list [dict] -> list [dict [str,str]]": 1,
            "tuple [int,...] -> int": 3,
            "iterable [token] -> int": 3,
            "optional [iterable [tuple [str,str,str]]] -> iterable [str]": 1,
            "bool -> iterable [str]": 1,
            "dict [union [int,str],union [int,float]] -> dict [...,...]": 4,
            "doc -> language": 1,
            "language -> doc": 1,
            "union [str,pathlib] -> types.pathlike": 1,
            "float -> optional [float]": 1,
            "list [docliketospans] -> list [types]": 1,
            "optional [docliketospans] -> optional [types]": 3,
            "iterable [tuple [str,dict]] -> iterable [types]": 7,
            "iterable [tuple [list [token],list [token],list [token]]] -> iterable [svotriple]": 1,
            "iterable [tuple [list [token],list [token],list [token]]] -> iterable [ssstriple]": 1,
            "iterable [tuple [list [token],list [token],span]] -> iterable [dqtriple]": 1,
            "tuple [augtransform] -> tuple [augtransform,...]": 1,
            "optional [collection [any]] -> collection [types]": 1,
            "set [any] -> set [types]": 1,
            "tuple [any,any] -> tuple [types,types]": 1,
            "tuple [augtransform,...] -> tuple [types,...]": 1,
            "list [augtransform] -> list [types]": 1,
            "list [aug_utils] -> list [types]": 8,
            "list [augtok] -> list [types]": 1,
            "sp.csr_matrix -> tuple [sp,dict [str,int],dict [str,int]]": 1,
            "iterator [doc] -> iterable [doc]": 1,
            "float -> dict [str,dict [str,int]]": 1,
            "int -> tuple [int,...]": 2,
            "int -> float": 1,
            "float -> iterable [token]": 1,
            "dict [str,dict [str,any]] -> dict [str,dict [str,types]]": 1
        },
        "s3": "------------------------------------------------------------------------",
        "RQ3_1": "Where are types added (function args, function returns, variables)?",
        "functionArgsType_added": 2110,
        "functionReturnsType_added": 803,
        "variableType_added": 280,
        "RQ3_2": "Where are types removed (function args, function returns, variables)?",
        "functionArgsType_removed": 1329,
        "functionReturnsType_removed": 438,
        "variableType_removed": 166,
        "RQ3_3": "Where are types changed (function args, function returns, variables?",
        "functionArgsType_changed": 165,
        "functionReturnsType_changed": 58,
        "variableType_changed": 19,
        "s4": "------------------------------------------------------------------------",
        "RQ4_1": "Are types added along with other changes around this code or in commits that only add types?",
        "typeAnnotation_added_per_commit": 0,
        "list_typeAnnotation_added_per_commit": [],
        "RQ4_2": "Are types removed along with other changes around this code or in commits that only add types?",
        "typeAnnotation_removed_per_commit": 0,
        "list_typeAnnotation_removed_per_commit": [],
        "RQ4_3": "Are types changed along with other changes around this code or in commits that only add types?",
        "typeAnnotation_changed_per_commit": 0,
        "list_typeAnnotation_changed_per_commit": [
            44.776119402985074,
            20.0,
            35.714285714285715,
            42.97520661157025,
            55.55555555555556,
            28.57142857142857,
            44.15584415584416,
            95.0,
            57.99999999999999,
            34.862385321100916,
            30.162412993039446,
            50.66666666666667,
            39.86013986013986,
            50.0,
            4.6875,
            7.03125,
            6.451612903225806,
            50.0,
            4.942688663618896,
            4.942688663618896,
            0.8695652173913043,
            0.6451612903225806,
            1.2048192771084338,
            10.0,
            16.666666666666664,
            4.918032786885246,
            14.285714285714285,
            29.411764705882355,
            2.3255813953488373,
            1.098901098901099,
            8.791208791208792,
            5.128205128205128,
            11.11111111111111,
            6.504065040650407,
            10.377358490566039,
            9.433962264150944,
            11.458333333333332,
            13.559322033898304,
            3.389830508474576,
            6.451612903225806,
            4.947916666666666,
            2.7777777777777777,
            1.5151515151515151,
            0.4329004329004329,
            12.5,
            26.666666666666668,
            4.0,
            6.25,
            8.333333333333332,
            1.9230769230769231,
            2.7777777777777777,
            2.7027027027027026,
            2.3255813953488373,
            3.0303030303030303,
            33.33333333333333,
            29.629629629629626,
            2.7777777777777777,
            33.33333333333333,
            2.941176470588235,
            9.31899641577061,
            3.4090909090909087,
            2.9069767441860463,
            2.7027027027027026,
            2.7027027027027026,
            4.861111111111112,
            4.081632653061225,
            5.555555555555555,
            2.2222222222222223,
            4.761904761904762,
            1.8072289156626504,
            9.090909090909092,
            0.6369426751592357,
            1.5015015015015014,
            8.323699421965317,
            8.323699421965317,
            44.0,
            19.17808219178082,
            12.790697674418606,
            2.9629629629629632,
            4.166666666666666,
            3.731343283582089,
            4.363357999489666,
            4.363357999489666,
            5.9405940594059405,
            0.9259259259259258,
            0.9803921568627451,
            1.9607843137254901,
            0.4878048780487805,
            1.0526315789473684,
            0.7936507936507936,
            1.36986301369863,
            1.36986301369863,
            2.272727272727273,
            2.857142857142857,
            3.3333333333333335,
            4.8582995951417,
            11.486486486486488,
            8.270676691729323,
            2.941176470588235,
            11.486486486486488,
            11.486486486486488,
            12.121212121212121,
            12.82051282051282,
            3.225806451612903,
            7.4074074074074066,
            8.333333333333332,
            3.9215686274509802,
            6.214039125431531,
            6.214039125431531,
            33.33333333333333,
            9.090909090909092,
            76.92307692307693,
            18.6046511627907,
            3.968253968253968,
            0.9708737864077669,
            0.3003003003003003,
            25.0,
            14.285714285714285,
            13.953488372093023,
            30.0,
            7.59493670886076,
            7.6923076923076925,
            5.555555555555555,
            52.63157894736842,
            7.142857142857142,
            5.555555555555555,
            2.127659574468085,
            3.4482758620689653,
            5.88235294117647,
            7.6923076923076925,
            7.142857142857142,
            4.166666666666666,
            5.263157894736842,
            2.484472049689441,
            2.484472049689441,
            11.11111111111111,
            1.7241379310344827,
            33.33333333333333,
            3.4482758620689653,
            5.084745762711865,
            1.639344262295082,
            0.5494505494505495,
            42.857142857142854,
            6.666666666666667,
            42.857142857142854,
            25.0,
            4.2105263157894735,
            4.3478260869565215,
            4.310344827586207,
            4.310344827586207,
            6.153846153846154,
            4.444444444444445,
            3.571428571428571,
            5.263157894736842,
            5.714285714285714,
            50.0,
            5.0,
            10.0,
            5.88235294117647,
            2.2222222222222223,
            2.0408163265306123,
            6.779661016949152,
            3.314917127071823,
            4.773869346733668,
            4.773869346733668,
            18.51851851851852,
            18.75,
            10.638297872340425,
            11.612903225806452,
            1.3888888888888888,
            2.0408163265306123,
            7.926829268292683,
            5.0,
            9.433962264150944,
            9.090909090909092,
            4.545454545454546,
            30.76923076923077,
            7.82608695652174,
            5.128205128205128,
            18.75,
            3.571428571428571,
            15.384615384615385,
            4.617414248021108,
            4.562737642585551,
            4.562737642585551,
            0.48543689320388345,
            2.0618556701030926,
            2.5,
            7.142857142857142,
            2.380952380952381,
            4.177545691906006,
            2.4390243902439024,
            3.9840637450199203,
            4.2042042042042045,
            50.0,
            0.2656042496679947,
            0.2656042496679947,
            26.08695652173913,
            16.666666666666664,
            6.666666666666667,
            12.5,
            33.33333333333333,
            11.428571428571429,
            25.0,
            25.0,
            85.71428571428571,
            2.5,
            3.225806451612903,
            25.0,
            13.043478260869565,
            25.0,
            7.6923076923076925,
            30.76923076923077,
            46.666666666666664,
            18.421052631578945,
            7.6923076923076925,
            35.38461538461539,
            16.43835616438356,
            30.625000000000004,
            20.168067226890756,
            7.207207207207207,
            31.46853146853147,
            14.723926380368098,
            4.545454545454546,
            8.571428571428571,
            8.98876404494382,
            11.538461538461538,
            7.236842105263158,
            3.0303030303030303,
            2.941176470588235,
            3.7037037037037033,
            4.365079365079365,
            3.8461538461538463,
            6.25,
            2.3255813953488373,
            4.861111111111112,
            16.666666666666664,
            6.857142857142858,
            0.5714285714285714,
            3.225806451612903,
            5.172413793103448,
            5.952380952380952,
            2.4691358024691357,
            28.57142857142857,
            16.666666666666664,
            7.207207207207207,
            3.4090909090909087,
            7.361963190184049,
            43.24324324324324,
            2.083333333333333,
            1.9801980198019802,
            2.7027027027027026,
            5.405405405405405,
            4.3478260869565215,
            4.166666666666666,
            2.4390243902439024,
            2.898550724637681,
            4.166666666666666,
            4.104477611940299,
            5.555555555555555,
            6.451612903225806,
            7.142857142857142,
            4.12621359223301,
            9.090909090909092,
            2.083333333333333,
            0.7936507936507936,
            5.263157894736842,
            5.263157894736842,
            3.5211267605633805,
            2.7522935779816518,
            5.88235294117647,
            11.11111111111111,
            14.285714285714285
        ],
        "annotation_related_insertion_edits_vs_all_commit": [],
        "annotation_related_deletion_edits_vs_all_commit": [],
        "s5": "------------------------------------------------------------------------",
        "RQ5": "Relation of properties of projects vs. properties of type changes.",
        "matrix_commits_stars_annotations": [
            [
                "2016",
                "1714",
                "1536",
                "5368",
                "209",
                "29",
                "959",
                "2683",
                "35",
                "0",
                "0",
                "32071"
            ]
        ],
        "matrix_files_annotations": [],
        "matrix_test_files_annotations": [],
        "dict_funct_call_no_types": {},
        "dict_funct_call_types": {},
        "s6": "------------------------------------------------------------------------",
        "RQ6": "Which are the top 10 repository with the highest number of type annotations.",
        "number_type_annotations_per_repo": {
            "https://github.com/chartbeat-labs/textacy": 5368
        },
        "s7": "------------------------------------------------------------------------",
        "RQ7": "How many of all types are annotated in the last version of the code?",
        "typeLastProjectVersion_total": 488,
        "typeLastProjectVersion_average": 0,
        "typeLastProjectVersion_percentage": [
            15.28
        ],
        "typeLastProjectVersion_dict": {
            "https://github.com/chartbeat-labs/textacy": 488
        },
        "typeLastProjectVersion_dict_error": {},
        "RQ8": "Total number of annotations over time, across all projects",
        "typeAnnotation_year_analysis": {
            "2020": 1881,
            "2021": 1312
        },
        "RQ9": "Total number of annotation-related commit over time, across all projects",
        "typeAnnotation_commit_annotation_year_analysis": {
            "2020": 34,
            "2021": 118
        },
        "typeAnnotation_commit_not_annotation_year_analysis": {
            "2020": 144,
            "2021": 258
        },
        "RQ10": "Type annotation coverage for each each",
        "annotation_coverage": {
            "2014": [
                0,
                0,
                0,
                0,
                0,
                0
            ],
            "2015": [
                0,
                0,
                0,
                0,
                0,
                0
            ],
            "2016": [
                0,
                774,
                0,
                369,
                0,
                1467
            ],
            "2017": [
                0,
                973,
                0,
                500,
                0,
                1804
            ],
            "2018": [
                0,
                3045,
                0,
                1754,
                0,
                6527
            ],
            "2019": [
                0,
                3020,
                0,
                1638,
                0,
                5792
            ],
            "2020": [
                1232,
                2476,
                460,
                1420,
                190,
                6370
            ]
        },
        "RQ11": "Developers statistics",
        "list_dev_dict": [
            {
                "chartbeat-labs-textacy": 0,
                "burtdewilde@gmail.com": 152
            }
        ],
        "list_dev_dict_total": [
            {
                "chartbeat-labs-textacy": 0,
                "burton@chartbeat.com": 539,
                "burtondewilde@gmail.com": 1,
                "burtdewilde@gmail.com": 1114,
                "andrew@inkblot.io": 1,
                "gbowyer@fastmail.co.uk": 1,
                "oroszgy@gmail.com": 1,
                "rndmax84@gmail.com": 1,
                "chuk.ovuworie@gmail.com": 1,
                "roland.kahlert@me.com": 1,
                "henri.dwyer@dataiku.com": 1,
                "rolando@users.noreply.github.com": 2,
                "pavlin99th@me.com": 1,
                "minketeer@users.noreply.github.com": 1,
                "gregory.f.howard@gmail.com": 1,
                "harryh@pitt.edu": 1,
                "mdlynch37@gmail.com": 1,
                "asif.mehedi@live.com": 1,
                "dominik.kloke@informatik.hu-berlin.de": 1,
                "moustachir.sami@gmail.com": 4,
                "sandy@saberr.com": 2,
                "scott.t.silliman@gmail.com": 13,
                "abevieiramota@gmail.com": 1,
                "ckot@users.noreply.github.com": 1,
                "34660048+digest0r@users.noreply.github.com": 1,
                "zfeng@localhost.local": 3,
                "zfeng@localhost.home": 1,
                "kiran.joshi@jisc.ac.uk": 5,
                "hugo_abonizio@hotmail.com": 1,
                "61438033+marius-mather@users.noreply.github.com": 1,
                "tbsexton@asu.edu": 5,
                "thurston.sexton@nist.gov": 2,
                "tim.gates@iress.com": 1,
                "austinjp@users.noreply.github.com": 1,
                "info@mirko-lenz.de": 2
            }
        ],
        "dev_dict": {},
        "dev_dict_total": {},
        "list_dev_plot": []
    }
]