[
    {
        "execution_time": "",
        "machine": {
            "OS": "Linux-4.15.0-166-generic-x86_64-with-Ubuntu-18.04-bionic",
            "CPU": "x86_64",
            "CORES": 48
        },
        "total_repositories": 1,
        "total_commits": 791,
        "commit_year_dict": {
            "2018": 116,
            "2019": 404,
            "2020": 125,
            "2021": 146
        },
        "loc_year_edit": {
            "2018": 231615,
            "2019": 54361,
            "2020": 18511,
            "2021": 7359
        },
        "s0": "------------------------------------------------------------------------",
        "RQ0": "How many types are used?",
        "code_changes": [],
        "commit_statistics": [],
        "repo_with_types_changes": 1,
        "percentage_repo_with_typeChanges": "",
        "commits_with_typeChanges": 98,
        "percentage_commits_with_typeChanges": "",
        "total_typeAnnotation_codeChanges": 2775,
        "s1": "------------------------------------------------------------------------",
        "RQ1": "Are type annotation inserted, removed and changed?",
        "insert_types": {
            "2018": 358,
            "2019": 1018,
            "2020": 37,
            "2021": 60
        },
        "percentage_insert_types": "",
        "remove_types": {
            "2018": 235,
            "2019": 887,
            "2020": 30,
            "2021": 2
        },
        "percentage_remove_types": "",
        "modify_existing_types": {
            "2018": 27,
            "2019": 104,
            "2020": 10,
            "2021": 7
        },
        "percentage_modify_existing_types": "",
        "s2": "------------------------------------------------------------------------",
        "RQ2_1": "What types are added (generic, numeric, ...)?",
        "anyType_added": 0,
        "noneType_added": 0,
        "numericType_added": 0,
        "binarySequenceType_added": 0,
        "textSequenceType_added": 0,
        "mappingTypes_added": 0,
        "setTypes_added": 0,
        "sequenceType_added": 0,
        "newType_added": 0,
        "total_added": 1473,
        "RQ2_2": "What are the top 5 types added?",
        "typeAdded_dict": {
            "symboltablenode": 7,
            "typechecker": 22,
            "str": 213,
            "bool": 53,
            "dict [str,'modelinfo']": 1,
            "dict [str,modelinfo]": 1,
            "callexpr": 11,
            "classdef": 13,
            "classdefcontext": 49,
            "attributecontext": 12,
            "inspect.boundarguments": 1,
            "none": 134,
            "type": 58,
            "optional [callable [...,none]]": 10,
            "optional [callable [...,type]]": 15,
            "djangomodelsregistry": 4,
            "semanticanalyzerplugininterface": 3,
            "types.type": 1,
            "nodes.assignmentstmt": 1,
            "datadriventestcase": 1,
            "functioncontext": 51,
            "instance": 34,
            "typeinfo": 73,
            "int": 13,
            "dict [str,argument]": 1,
            "options": 3,
            "any": 7,
            "settings": 2,
            "'datadriventestcase'": 1,
            "'datasuitecollector'": 1,
            "'datasuite'": 1,
            "object": 2,
            "iterator [djangodatadriventestcase]": 1,
            "iterator [pytest]": 2,
            "'optional[any]'": 1,
            "typing.type": 1,
            "apps": 1,
            "buildmanager": 4,
            "list [str]": 32,
            "state": 1,
            "list [buildsource]": 5,
            "optional [graph]": 3,
            "optional [list [state]]": 3,
            "list [type]": 4,
            "optional [sequence [optional [str]]]": 3,
            "list [list [int]]": 2,
            "list [expression]": 3,
            "optional [type]": 8,
            "context": 8,
            "callable [...,none]": 5,
            "optional [tuple [int,list [str]]]": 1,
            "dict [str,createfile]": 1,
            "path": 7,
            "'mypytestscollector'": 1,
            "type [mypytypechecktestcase]": 1,
            "optional [str]": 21,
            "optional [list [str]]": 4,
            "optional [dict [str,createfile]]": 1,
            "optional [dict [str,any]]": 4,
            "exceptioninfo": 1,
            "type ['mypytypechecktestcase']": 1,
            "optional [mypytestscollector]": 1,
            "optional [typeinfo]": 13,
            "list [int]": 1,
            "optional [expression]": 4,
            "optional [messagebuilder]": 1,
            "tuple [type,type]": 1,
            "graph": 3,
            "set [str]": 15,
            "optional [abstractset [str]]": 1,
            "list [abstractset [str]]": 1,
            "list [assignmentstmt]": 1,
            "semanticanalyzerpass2": 10,
            "statement": 1,
            "iterator [tuple [lvalue,expression]]": 1,
            "iterator [tuple [lvalue,callexpr]]": 2,
            "iterator [tuple [nameexpr,callexpr]]": 2,
            "iterator [classdef]": 2,
            "optional [instance]": 11,
            "symbolnode": 2,
            "uniontype": 2,
            "mypyfile": 12,
            "dict [str,mypyfile]": 6,
            "dict [str,int]": 11,
            "methodcontext": 33,
            "expression": 7,
            "'config'": 2,
            "dict [str,type]": 4,
            "dict [str,any]": 13,
            "list [tuple [str,typeinfo]]": 2,
            "iterable [mypyfile]": 2,
            "union [uniontype,instance]": 2,
            "optional [symboltablenode]": 3,
            "checkerplugininterface": 9,
            "list [lookupnode]": 2,
            "lookupnode": 4,
            "union [anytype,type]": 1,
            "list [optional [str]]": 1,
            "ordereddict [str,type]": 2,
            "list [tuple [int,str,int]]": 3,
            "analyzetypecontext": 5,
            "dict [str,str]": 3,
            "optional [dict [str,str]]": 10,
            "lazysettings": 5,
            "dict [str,list [type [model]]]": 6,
            "tuple ['apps','lazysettings']": 3,
            "optional [type [model]]": 4,
            "list [mypytype]": 4,
            "union [functioncontext,methodcontext]": 8,
            "mypytype": 84,
            "optional [symbolnode]": 3,
            "optional [mypytype]": 3,
            "optional [bool]": 3,
            "djangocontext": 48,
            "tuple [int,str,int]": 2,
            "optional [callable [...,mypytype]]": 6,
            "tuple [mypytype,mypytype]": 2,
            "newsemanticanalyzer": 2,
            "field": 24,
            "type [model]": 35,
            "argument": 1,
            "iterator [field]": 3,
            "dict [str,mypytype]": 3,
            "'djangocontext'": 5,
            "list [instance]": 3,
            "'ordereddict[str, mypytype]'": 8,
            "var": 2,
            "'typechecker'": 2,
            "tupletype": 5,
            "typeddicttype": 2,
            "optional [typetype]": 2,
            "optional [tuple [str,mypytype]]": 2,
            "iterator [foreignobjectrel]": 2,
            "union [methodcontext,functioncontext]": 1,
            "list [tuple [str,mypytype]]": 1,
            "sequence [expression]": 1,
            "yamltestitem": 1,
            "union [attributecontext,methodcontext,functioncontext]": 2,
            "union [relatedfield,foreignobjectrel]": 1,
            "union [pattern,str]": 1,
            "dict [str,dict [str,int]]": 1,
            "dict [str,dict [union [str,pattern],int]]": 1,
            "iterable [str]": 1,
            "dict [str,set [type [model]]]": 1,
            "functiondef": 3,
            "baseexpression": 1,
            "name": 1,
            "funcdef": 4,
            "repo": 3,
            "dict [str,tuple [str,str]]": 1,
            "tuple [list [argument],mypytype]": 1,
            "dynamicclassdefcontext": 1,
            "noreturn": 2,
            "optional [int]": 2,
            "type [_t]": 3,
            "list [mpgeneric [any]]": 2,
            "_versionspec": 1,
            "optional [_versionspec]": 3,
            "fixturerequest": 1,
            "monkeypatch": 1,
            "_makegenericclasses": 4,
            "optional [list [instance]]": 1,
            "union [semanticanalyzer,checkerplugininterface]": 1,
            "optional [typeddicttype]": 1,
            "semanticanalyzer": 1
        },
        "RQ2_3": "What types are removed (generic, numeric, ...)?",
        "anyType_removed": 0,
        "noneType_removed": 0,
        "numericType_removed": 0,
        "binarySequenceType_removed": 0,
        "textSequenceType_removed": 0,
        "mappingTypes_removed": 0,
        "setTypes_removed": 0,
        "sequenceType_removed": 0,
        "newType_removed": 0,
        "total_removed": 1154,
        "RQ2_4": "What are the top 5 types removed?",
        "typeRemoved_dict": {
            "dict [str,'modelinfo']": 1,
            "callexpr": 11,
            "classdef": 16,
            "str": 170,
            "classdefcontext": 42,
            "attributecontext": 11,
            "inspect.boundarguments": 1,
            "none": 83,
            "type": 51,
            "optional [callable [...,none]]": 8,
            "optional [callable [...,type]]": 8,
            "djangomodelsregistry": 4,
            "set [str]": 14,
            "bool": 47,
            "semanticanalyzerplugininterface": 1,
            "types.type": 1,
            "nodes.assignmentstmt": 1,
            "symboltablenode": 5,
            "typechecker": 12,
            "instance": 25,
            "any": 6,
            "settings": 2,
            "apps": 1,
            "buildmanager": 4,
            "list [str]": 30,
            "state": 1,
            "list [buildsource]": 5,
            "optional [graph]": 3,
            "optional [list [state]]": 3,
            "list [type]": 3,
            "optional [sequence [optional [str]]]": 3,
            "list [list [int]]": 2,
            "list [expression]": 3,
            "int": 9,
            "optional [type]": 6,
            "context": 6,
            "object": 2,
            "functioncontext": 35,
            "list [assignmentstmt]": 1,
            "optional [any]": 1,
            "'datadriventestcase'": 1,
            "'datasuitecollector'": 1,
            "'datasuite'": 1,
            "iterator [djangodatadriventestcase]": 1,
            "iterator [pytest]": 2,
            "'optional[any]'": 1,
            "callable [...,none]": 5,
            "optional [tuple [int,list [str]]]": 1,
            "dict [str,createfile]": 1,
            "path": 7,
            "'mypytestscollector'": 1,
            "type [mypytypechecktestcase]": 1,
            "optional [str]": 24,
            "optional [list [str]]": 3,
            "optional [dict [str,createfile]]": 1,
            "optional [dict [str,any]]": 4,
            "exceptioninfo": 1,
            "type ['mypytypechecktestcase']": 1,
            "optional [mypytestscollector]": 1,
            "datadriventestcase": 1,
            "semanticanalyzerpass2": 9,
            "statement": 1,
            "typeinfo": 66,
            "iterator [classdef]": 3,
            "optional [typeinfo]": 11,
            "list [int]": 1,
            "optional [expression]": 8,
            "optional [messagebuilder]": 1,
            "tuple [type,type]": 1,
            "iterator [tuple [lvalue,expression]]": 1,
            "graph": 3,
            "optional [abstractset [str]]": 1,
            "list [abstractset [str]]": 1,
            "'config'": 3,
            "iterator [tuple [lvalue,callexpr]]": 2,
            "dict [str,any]": 13,
            "methodcontext": 20,
            "dict [str,type]": 4,
            "expression": 8,
            "optional [instance]": 10,
            "mypyfile": 12,
            "dict [str,mypyfile]": 10,
            "iterator [tuple [nameexpr,callexpr]]": 3,
            "list [tuple [str,typeinfo]]": 2,
            "symbolnode": 2,
            "uniontype": 2,
            "iterable [mypyfile]": 2,
            "optional [symboltablenode]": 3,
            "union [uniontype,instance]": 2,
            "union [anytype,type]": 1,
            "checkerplugininterface": 10,
            "list [lookupnode]": 2,
            "lookupnode": 4,
            "optional [dict [str,str]]": 10,
            "lazysettings": 5,
            "dict [str,list [type [model]]]": 4,
            "tuple ['apps','lazysettings']": 2,
            "optional [type [model]]": 3,
            "mypytype": 48,
            "field": 13,
            "type [model]": 15,
            "argument": 1,
            "djangocontext": 23,
            "dict [str,str]": 3,
            "list [mypytype]": 5,
            "union [functioncontext,methodcontext]": 7,
            "'typechecker'": 6,
            "union [classdef,mypyfile]": 1,
            "'ordereddict[str, mypytype]'": 6,
            "var": 3,
            "optional [mypyfile]": 2,
            "optional [symbolnode]": 2,
            "optional [bool]": 3,
            "optional [mypytype]": 6,
            "iterator [tuple [str,expression]]": 3,
            "typeddicttype": 2,
            "tupletype": 3,
            "iterator [tuple [str,callexpr]]": 2,
            "options": 2,
            "dict [str,int]": 8,
            "list [tuple [int,str,int]]": 2,
            "ordereddict [str,type]": 2,
            "list [optional [str]]": 1,
            "analyzetypecontext": 3,
            "'djangocontext'": 3,
            "iterator [field]": 2,
            "iterator [foreignobjectrel]": 2,
            "dict [str,mypytype]": 2,
            "list [instance]": 1,
            "tuple [int,str,int]": 1,
            "optional [callable [...,mypytype]]": 4,
            "tuple [mypytype,mypytype]": 1,
            "optional [typetype]": 1,
            "union [methodcontext,functioncontext]": 1,
            "list [tuple [str,mypytype]]": 1,
            "newsemanticanalyzer": 2,
            "optional [tuple [str,mypytype]]": 2,
            "dict [str,set [type [model]]]": 2,
            "funcdef": 2,
            "tuple [list [argument],mypytype]": 1,
            "functiondef": 3,
            "baseexpression": 1,
            "name": 1,
            "repo": 1,
            "optional [int]": 1,
            "type [_t]": 2,
            "optional [_versionspec]": 1,
            "list [mpgeneric [any]]": 1
        },
        "RQ2_5": "What types are the top 10 changed ?",
        "total_changed": 148,
        "typeChanged_dict_var": {
            "dict [str,modelinfo] -> set [str]": 1,
            "dict [str,list [type [model]]] -> dict [str,set [type [model]]]": 1,
            "semanticanalyzerplugininterface -> semanticanalyzer": 1,
            "'ordereddict[str, mypytype]' -> \"ordereddict[str, mypytype]\"": 2,
            "dict [str,tuple [str,str]] -> dict [str,str]": 1
        },
        "typeChanged_dict_arg": {
            "str -> optional [str]": 1,
            "functioncontext -> classdefcontext": 2,
            "functioncontext -> analyzetypecontext": 1,
            "analyzetypecontext -> attributecontext": 1,
            "semanticanalyzerpass2 -> 'typechecker'": 1,
            "classdefcontext -> attributecontext": 1,
            "functioncontext -> union [methodcontext,functioncontext]": 1,
            "methodcontext -> union [functioncontext,methodcontext]": 1,
            "analyzetypecontext -> functioncontext": 1,
            "functioncontext -> methodcontext": 1,
            "set [str] -> iterable [str]": 1,
            "instance -> mypytype": 2,
            "typechecker -> union [typechecker,semanticanalyzer]": 1,
            "'ordereddict[str, mypytype]' -> optional [dict [str,mypytype]]": 1,
            "union [attributecontext,methodcontext,functioncontext] -> union [classdefcontext,dynamicclassdefcontext]": 1,
            "field -> union [field,foreignobjectrel]": 4,
            "'ordereddict[str, mypytype]' -> \"ordereddict[str, mypytype]\"": 2,
            "'typechecker' -> \"typechecker\"": 1,
            "'djangocontext' -> \"djangocontext\"": 2,
            "optional [int] -> optional [_versionspec]": 1
        },
        "typeChanged_dict_ret": {
            "type -> optional [callable [...,none]]": 1,
            "none -> type": 7,
            "type -> optional [type]": 1,
            "optional [callable [...,type]] -> type": 1,
            "optional [type] -> optional [instance]": 1,
            "type -> symboltablenode": 1,
            "optional [callable [...,type]] -> none": 1,
            "bool -> symboltablenode": 1,
            "symboltablenode -> optional [dict [str,argument]]": 1,
            "symboltablenode -> none": 1,
            "str -> none": 2,
            "none -> optional [any]": 1,
            "bool -> iterator [classdef]": 1,
            "iterator [classdef] -> optional [instance]": 1,
            "optional [typeinfo] -> bool": 1,
            "optional [instance] -> optional [str]": 2,
            "symboltablenode -> optional [symboltablenode]": 1,
            "none -> optional [typeinfo]": 1,
            "optional [typeinfo] -> none": 1,
            "bool -> none": 1,
            "none -> iterator [classdef]": 1,
            "optional [callable [...,type]] -> dict [str,int]": 2,
            "none -> iterator [tuple [lvalue,expression]]": 1,
            "type -> optional [str]": 1,
            "none -> bool": 5,
            "int -> str": 1,
            "none -> 'config'": 1,
            "type -> set [str]": 1,
            "set [str] -> none": 1,
            "bool -> optional [expression]": 1,
            "bool -> optional [instance]": 1,
            "iterator [tuple [lvalue,expression]] -> iterator [tuple [lvalue,callexpr]]": 1,
            "optional [type] -> optional [str]": 1,
            "type -> optional [typeinfo]": 1,
            "optional [type] -> type": 1,
            "type -> none": 3,
            "optional [typeinfo] -> optional [expression]": 1,
            "type -> instance": 1,
            "optional [callable [...,type]] -> list [str]": 1,
            "optional [callable [...,type]] -> optional [typeinfo]": 1,
            "iterator [tuple [lvalue,callexpr]] -> iterator [tuple [nameexpr,callexpr]]": 1,
            "optional [instance] -> none": 1,
            "iterator [classdef] -> dict [str,any]": 1,
            "optional [instance] -> bool": 1,
            "context -> optional [symboltablenode]": 1,
            "list [type] -> type": 1,
            "optional [symboltablenode] -> type": 1,
            "optional [callable [...,type]] -> optional [callable [...,none]]": 1,
            "none -> optional [str]": 1,
            "iterator [tuple [nameexpr,callexpr]] -> none": 1,
            "none -> iterator [tuple [nameexpr,callexpr]]": 1,
            "none -> expression": 1,
            "instance -> optional [typeinfo]": 1,
            "optional [callable [...,none]] -> optional [callable [...,type]]": 1,
            "mypytype -> list [tuple [str,mypytype]]": 1,
            "mypytype -> none": 1,
            "field -> iterator [foreignobjectrel]": 1,
            "optional [symbolnode] -> optional [symboltablenode]": 1,
            "none -> mypytype": 2,
            "mypytype -> typeinfo": 1,
            "optional [callable [...,type]] -> optional [callable [...,mypytype]]": 1,
            "any -> optional [field]": 1,
            "str -> optional [str]": 1,
            "mypytype -> optional [list [str]]": 1,
            "optional [field] -> field": 1,
            "typeinfo -> optional [typeinfo]": 2,
            "none -> var": 1,
            "optional [str] -> optional [field]": 1,
            "none -> str": 1,
            "dict [str,int] -> none": 1,
            "tupletype -> mypyfile": 1,
            "mypytype -> optional [mypytype]": 1,
            "mypytype -> optional [instance]": 1,
            "dict [str,list [type [model]]] -> dict [str,set [type [model]]]": 1,
            "set [str] -> bool": 1,
            "field -> mypytype": 1,
            "mypytype -> iterator [instance]": 1,
            "optional [typeinfo] -> mypytype": 1,
            "str -> dict [str,set [type [model]]]": 1,
            "type [model] -> optional [type [model]]": 1,
            "set [str] -> set [type [models]]": 1,
            "str -> set [str]": 1,
            "mypytype -> instance": 1,
            "none -> tuple [list [argument],mypytype]": 1,
            "repo -> none": 1,
            "typechecker -> semanticanalyzer": 1,
            "bool -> typechecker": 1,
            "field -> union [field,foreignobjectrel]": 2,
            "none -> typeinfo": 1,
            "tuple ['apps','lazysettings'] -> tuple [\"apps\",\"lazysettings\"]": 1,
            "none -> dict [str,str]": 1,
            "optional [symboltablenode] -> bool": 1,
            "instance -> mypytype": 1,
            "typeinfo -> bool": 1,
            "optional [callable [...,none]] -> optional [callable [...,mypytype]]": 1,
            "optional [list [str]] -> optional [dict [str,mypytype]]": 1,
            "none -> optional [mypytype]": 1
        },
        "s3": "------------------------------------------------------------------------",
        "RQ3_1": "Where are types added (function args, function returns, variables)?",
        "functionArgsType_added": 862,
        "functionReturnsType_added": 518,
        "variableType_added": 93,
        "RQ3_2": "Where are types removed (function args, function returns, variables)?",
        "functionArgsType_removed": 676,
        "functionReturnsType_removed": 397,
        "variableType_removed": 81,
        "RQ3_3": "Where are types changed (function args, function returns, variables?",
        "functionArgsType_changed": 27,
        "functionReturnsType_changed": 115,
        "variableType_changed": 6,
        "s4": "------------------------------------------------------------------------",
        "RQ4_1": "Are types added along with other changes around this code or in commits that only add types?",
        "typeAnnotation_added_per_commit": 0,
        "list_typeAnnotation_added_per_commit": [],
        "RQ4_2": "Are types removed along with other changes around this code or in commits that only add types?",
        "typeAnnotation_removed_per_commit": 0,
        "list_typeAnnotation_removed_per_commit": [],
        "RQ4_3": "Are types changed along with other changes around this code or in commits that only add types?",
        "typeAnnotation_changed_per_commit": 0,
        "list_typeAnnotation_changed_per_commit": [
            7.179487179487179,
            6.134969325153374,
            6.024096385542169,
            0.30303030303030304,
            3.6101083032490973,
            4.142011834319527,
            0.22371364653243847,
            1.4925373134328357,
            2.197802197802198,
            8.0,
            10.0,
            2.7777777777777777,
            1.2552301255230125,
            4.395604395604396,
            6.4655172413793105,
            0.6153846153846154,
            9.58904109589041,
            3.296703296703297,
            4.591836734693878,
            12.121212121212121,
            1.3377926421404682,
            3.9473684210526314,
            9.615384615384617,
            3.801546391752577,
            1.5873015873015872,
            0.05955926146515784,
            6.51685393258427,
            5.277777777777778,
            0.12406947890818859,
            0.45871559633027525,
            3.233256351039261,
            1.1494252873563218,
            4.371584699453552,
            4.054054054054054,
            1.8518518518518516,
            4.225352112676056,
            1.6483516483516485,
            3.8461538461538463,
            4.3478260869565215,
            0.9478672985781991,
            4.545454545454546,
            6.862745098039216,
            0.5681818181818182,
            3.0927835051546393,
            5.714285714285714,
            2.5,
            4.0,
            4.761904761904762,
            1.5873015873015872,
            2.0,
            1.5789473684210527,
            0.3389830508474576,
            2.2222222222222223,
            3.0470914127423825,
            1.3966480446927374,
            0.2145922746781116,
            6.8493150684931505,
            1.2658227848101267,
            1.8072289156626504,
            1.5384615384615385,
            0.43103448275862066,
            4.159132007233273,
            3.4220532319391634,
            0.4878048780487805,
            1.5873015873015872,
            3.8461538461538463,
            1.2987012987012987,
            0.9615384615384616,
            3.3112582781456954,
            6.779661016949152,
            0.9433962264150944,
            6.730769230769231,
            0.684931506849315,
            5.0,
            5.221932114882506,
            6.0364464692482915,
            0.04930966469428008,
            0.7142857142857143,
            4.761904761904762,
            2.2222222222222223,
            4.3478260869565215,
            4.545454545454546,
            2.1505376344086025,
            8.333333333333332,
            2.877697841726619,
            3.0927835051546393,
            4.838709677419355,
            2.73224043715847,
            0.78125,
            5.0,
            1.9607843137254901,
            0.424929178470255,
            1.8518518518518516,
            2.7777777777777777,
            0.13869625520110956,
            1.1494252873563218,
            2.736318407960199,
            5.409836065573771,
            0.9803921568627451,
            4.6875,
            1.7591339648173208,
            1.0810810810810811,
            2.0344287949921753,
            0.29142381348875934,
            0.08719662839703532,
            8.524590163934425,
            3.67965367965368,
            0.5188067444876783,
            2.941176470588235,
            5.128205128205128,
            0.9259259259259258,
            11.29032258064516,
            5.454545454545454,
            0.847457627118644,
            4.576271186440678,
            1.079136690647482,
            0.34782608695652173,
            6.597361055577769,
            2.857142857142857,
            2.8579356270810212,
            2.717391304347826,
            1.3274336283185841,
            1.1299435028248588,
            0.5,
            16.666666666666664,
            12.5,
            25.0,
            1.6129032258064515,
            14.634146341463413,
            0.33444816053511706,
            2.380952380952381,
            2.083333333333333,
            6.25,
            6.25,
            6.8493150684931505,
            3.571428571428571,
            1.9417475728155338,
            0.7194244604316548,
            3.125,
            8.19672131147541,
            5.084745762711865,
            1.639344262295082,
            0.23837902264600713,
            20.0,
            2.4242424242424243,
            4.3478260869565215,
            1.0600706713780919,
            6.521739130434782,
            4.878048780487805,
            1.8518518518518516,
            2.272727272727273,
            3.8461538461538463,
            1.4285714285714286,
            4.761904761904762,
            5.88235294117647,
            8.0,
            8.333333333333332,
            2.0,
            5.0,
            6.451612903225806,
            2.013422818791946,
            0.8080808080808081,
            5.454545454545454,
            5.752212389380531,
            0.3976143141153081,
            1.5151515151515151,
            3.896103896103896,
            5.063291139240507,
            3.1578947368421053,
            4.958677685950414,
            7.142857142857142,
            4.0,
            1.694915254237288,
            0.8,
            12.5,
            2.7027027027027026,
            2.0,
            5.223880597014925,
            1.1627906976744187,
            1.9390581717451523,
            10.714285714285714,
            16.666666666666664,
            3.571428571428571,
            1.4285714285714286,
            1.0869565217391304,
            3.225806451612903,
            1.834862385321101,
            0.05873140172278779,
            0.2401625715869204,
            0.08547008547008547,
            2.690582959641256,
            2.380952380952381,
            0.6666666666666667,
            11.538461538461538,
            7.792207792207792,
            2.564102564102564,
            5.47945205479452,
            1.2987012987012987,
            5.0,
            2.9629629629629632,
            0.6451612903225806,
            6.451612903225806,
            12.5,
            1.4084507042253522,
            2.857142857142857,
            1.9836639439906651,
            0.30612244897959184,
            3.90625,
            0.6211180124223602,
            5.263157894736842,
            10.0,
            4.9504950495049505
        ],
        "annotation_related_insertion_edits_vs_all_commit": [],
        "annotation_related_deletion_edits_vs_all_commit": [],
        "s5": "------------------------------------------------------------------------",
        "RQ5": "Relation of properties of projects vs. properties of type changes.",
        "matrix_commits_stars_annotations": [
            [
                "2018",
                "791",
                "509",
                "2775",
                "113",
                "111",
                "249",
                "670",
                "150",
                "0",
                "0",
                "2259"
            ]
        ],
        "matrix_files_annotations": [],
        "matrix_test_files_annotations": [],
        "dict_funct_call_no_types": {},
        "dict_funct_call_types": {},
        "s6": "------------------------------------------------------------------------",
        "RQ6": "Which are the top 10 repository with the highest number of type annotations.",
        "number_type_annotations_per_repo": {
            "https://github.com/typeddjango/django-stubs": 2775
        },
        "s7": "------------------------------------------------------------------------",
        "RQ7": "How many of all types are annotated in the last version of the code?",
        "typeLastProjectVersion_total": 439,
        "typeLastProjectVersion_average": 0,
        "typeLastProjectVersion_percentage": [
            29.8
        ],
        "typeLastProjectVersion_dict": {
            "https://github.com/typeddjango/django-stubs": 439
        },
        "typeLastProjectVersion_dict_error": {},
        "RQ8": "Total number of annotations over time, across all projects",
        "typeAnnotation_year_analysis": {
            "2018": 358,
            "2019": 1018,
            "2020": 37,
            "2021": 60
        },
        "RQ9": "Total number of annotation-related commit over time, across all projects",
        "typeAnnotation_commit_annotation_year_analysis": {
            "2018": 20,
            "2019": 63,
            "2020": 6,
            "2021": 9
        },
        "typeAnnotation_commit_not_annotation_year_analysis": {
            "2018": 63,
            "2019": 325,
            "2020": 55,
            "2021": 113
        },
        "RQ10": "Type annotation coverage for each each",
        "annotation_coverage": {
            "2014": [
                0,
                0,
                0,
                0,
                0,
                0
            ],
            "2015": [
                0,
                0,
                0,
                0,
                0,
                0
            ],
            "2016": [
                0,
                0,
                0,
                0,
                0,
                0
            ],
            "2017": [
                0,
                0,
                0,
                0,
                0,
                0
            ],
            "2018": [
                0,
                1,
                0,
                1,
                0,
                6
            ],
            "2019": [
                152,
                52,
                94,
                10,
                3,
                343
            ],
            "2020": [
                1023,
                399,
                644,
                74,
                31,
                2404
            ]
        },
        "RQ11": "Developers statistics",
        "list_dev_dict": [
            {
                "typeddjango-django-stubs": 0,
                "maxim.kurnikov@gmail.com": 78,
                "syastrov@gmail.com": 8,
                "saras.nejuz@gmail.com": 1,
                "nhirschfeld@gmail.com": 1,
                "51172302+3n-k1@users.noreply.github.com": 1,
                "mail@sobolevn.me": 5,
                "51172302+void-witch@users.noreply.github.com": 1,
                "mail@kalekseev.com": 1,
                "git@thequod.de": 1,
                "cesar.canassa@gmail.com": 1
            }
        ],
        "list_dev_dict_total": [
            {
                "typeddjango-django-stubs": 0,
                "maxim.kurnikov@gmail.com": 420,
                "lukewm@riseup.net": 8,
                "lwm@users.noreply.github.com": 3,
                "mes@3yourmind.com": 1,
                "github@naddiseo.ca": 2,
                "juravel2@gmail.com": 7,
                "aleksanderburkow@gmail.com": 7,
                "rune.steinnes@westum.no": 2,
                "syastrov@gmail.com": 21,
                "mattbasta+github@gmail.com": 1,
                "mail@kalekseev.com": 8,
                "1kroolik1@gmail.com": 1,
                "anthony@ricaud.me": 8,
                "aszlig@redmoonstudios.org": 1,
                "ethan@ethanhs.me": 1,
                "ville.skytta@iki.fi": 2,
                "ran234@gmail.com": 1,
                "git@antonagestam.se": 7,
                "PeterJCLaw@gmail.com": 5,
                "mail@sobolevn.me": 57,
                "swenkooij@gmail.com": 1,
                "pwbdecker@gmail.com": 1,
                "wlisesrivas@gmail.com": 1,
                "github@thequod.de": 1,
                "git@thequod.de": 6,
                "soapAnd@gmail.com": 1,
                "yngve@hoiseth.net": 1,
                "anna@takkaria.org": 1,
                "premium@sawrc.com": 1,
                "ccordero@protonmail.com": 1,
                "filip.lajszczak@gmail.com": 1,
                "yaegassy@users.noreply.github.com": 1,
                "775.pg.12@gmail.com": 2,
                "yms@outlook.com": 1,
                "youssef@color.com": 1,
                "ran@unusedvar.com": 1,
                "hannes@5monkeys.se": 8,
                "6639509+henribru@users.noreply.github.com": 2,
                "lambdadmitry@gmail.com": 1,
                "jrheard@cs.stanford.edu": 1,
                "marti@juffo.org": 14,
                "kotvberloge@gmail.com": 1,
                "daniel.hillier@gmail.com": 6,
                "cesar.canassa@gmail.com": 3,
                "josephbkahn@gmail.com": 1,
                "Tatsh@users.noreply.github.com": 1,
                "salvino@coderedcorp.com": 1,
                "brian.helba@kitware.com": 8,
                "semen.pupkov@gmail.com": 2,
                "leo@thermopylae.net": 1,
                "kevinmarsh@users.noreply.github.com": 2,
                "stevan.milic@yahoo.com": 2,
                "github.com@qtea.nl": 1,
                "sidmitra.del@gmail.com": 1,
                "szmigielkacper@gmail.com": 10,
                "onyekaag@gmail.com": 1,
                "zimbler@gmail.com": 1,
                "jorgenphillips@gmail.com": 1,
                "bansal.ashish096@gmail.com": 1,
                "asfaltboy@gmail.com": 2,
                "viklu@kth.se": 2,
                "alex.viklund@gmail.com": 5,
                "michael-k@users.noreply.github.com": 1,
                "ceesjan@ytec.nl": 2,
                "yellowbounder@gmail.com": 1,
                "et@hossack.me": 1,
                "Anelander@gmail.com": 1,
                "natec425@gmail.com": 1,
                "544451+ljodal@users.noreply.github.com": 2,
                "sirexas@gmail.com": 1,
                "saras.nejuz@gmail.com": 1,
                "federicobond@gmail.com": 1,
                "bullfest@sthlm.dev": 3,
                "zach.waggoner1@gmail.com": 1,
                "jameslp@umich.edu": 1,
                "a-musing-moose@users.noreply.github.com": 1,
                "zefciu@gmail.com": 1,
                "ticosax@free.fr": 1,
                "wkschwartz@gmail.com": 3,
                "mrf.mariam@gmail.com": 1,
                "nhirschfeld@gmail.com": 2,
                "noamkush@users.noreply.github.com": 1,
                "mark@mark-story.com": 1,
                "51172302+3n-k1@users.noreply.github.com": 6,
                "gilad97@gmail.com": 1,
                "41123800+yankyhoffman@users.noreply.github.com": 1,
                "robert@huseli.us": 1,
                "clarity@ridereportapp.com": 1,
                "franklapedriza@gmail.com": 1,
                "tim@asymptotic.co.uk": 2,
                "31746850+javulticat@users.noreply.github.com": 1,
                "lambdalisue@hashnote.net": 1,
                "lisandrosnik@gmail.com": 1,
                "marcin@marcin.co": 1,
                "51172302+void-witch@users.noreply.github.com": 1,
                "earth2mark@gmail.com": 2,
                "anas.el.amraoui@live.com": 1,
                "gabor@20y.hu": 1,
                "jpulec@gmail.com": 2,
                "okapies@gmail.com": 1,
                "nicolas.delaby@infarm.com": 1,
                "charettes@users.noreply.github.com": 1,
                "github@chasnelson.co.uk": 1,
                "t.krapp@googlemail.com": 2,
                "danthedeckie@users.noreply.github.com": 1,
                "78786958+melvyn-oviavo@users.noreply.github.com": 1,
                "jamesowen@outlook.com": 1,
                "e@grubbs.org": 1,
                "highpost@users.noreply.github.com": 1,
                "coding+github@khaleesi.ninja": 3,
                "charette.s@gmail.com": 2,
                "13880786+abhiabhi94@users.noreply.github.com": 4,
                "maxim@masiutin.com": 1,
                "32638720+henzef@users.noreply.github.com": 1,
                "sondrelg@live.no": 1,
                "bob.whitelock1@gmail.com": 1,
                "32252655+ykiu@users.noreply.github.com": 1,
                "pawmar@gmail.com": 1,
                "43341786+abhishek0220@users.noreply.github.com": 2,
                "jon@jon-foster.co.uk": 1,
                "maarten@treewalker.org": 1,
                "smileychris@gmail.com": 5,
                "darius@blink.net": 1,
                "davidszotten@gmail.com": 1,
                "michaelaquilina@gmail.com": 4,
                "__Singleton__@hackerdom.ru": 1,
                "petter@5monkeys.se": 1,
                "tim.nyborg@gmail.com": 3,
                "41898282+github-actions[bot]@users.noreply.github.com": 1,
                "satya.devel@gmail.com": 2,
                "80257277+mwilliamson-foodsteps@users.noreply.github.com": 1,
                "richardxia@richardxia.com": 2,
                "39874143+PIG208@users.noreply.github.com": 3,
                "eero.ruohola@icloud.com": 1,
                "eero@ruohola.dev": 1,
                "41215134+c-py@users.noreply.github.com": 1,
                "terence@honles.com": 3,
                "rob.percival@krakentechnologies.ltd": 1,
                "i@star2000.work": 1,
                "untidyhair@gmail.com": 1,
                "petter_friberg@hotmail.com": 1,
                "avery@averyjfischer.com": 1,
                "davidjosephcain@gmail.com": 1,
                "54817925+StasGC@users.noreply.github.com": 1,
                "imamatory@users.noreply.github.com": 1,
                "w0rp@users.noreply.github.com": 2,
                "gabriel@augendre.info": 2,
                "corydolphin@gmail.com": 1,
                "carljohan.hambro@gmail.com": 1
            }
        ],
        "dev_dict": {},
        "dev_dict_total": {},
        "list_dev_plot": []
    }
]